{
  "version": 1,
  "title": "PASSAGE_P9_C12",
  "durationMinutes": 60,
  "examTrack": "ielts",
  "parts": [
    {
      "partNumber": 1,
      "rangeLabel": "",
      "passageTitle": "Green roofs",
      "passage": [
        {
          "text": "A."
        },
        {
          "text": "Rooftops"
        },
        {
          "text": "covered"
        },
        {
          "text": "with"
        },
        {
          "text": "grass,"
        },
        {
          "text": "vegetable"
        },
        {
          "text": "gardens"
        },
        {
          "text": "and"
        },
        {
          "text": "lush"
        },
        {
          "text": "foliage"
        },
        {
          "text": "are"
        },
        {
          "text": "now"
        },
        {
          "text": "a"
        },
        {
          "text": "common"
        },
        {
          "text": "sight"
        },
        {
          "text": "in"
        },
        {
          "text": "many"
        },
        {
          "text": "cities"
        },
        {
          "text": "around"
        },
        {
          "text": "the"
        },
        {
          "text": "world."
        },
        {
          "text": "More"
        },
        {
          "text": "and"
        },
        {
          "text": "more"
        },
        {
          "text": "private"
        },
        {
          "text": "companies"
        },
        {
          "text": "and"
        },
        {
          "text": "city"
        },
        {
          "text": "authorities"
        },
        {
          "text": "are"
        },
        {
          "text": "investing"
        },
        {
          "text": "in"
        },
        {
          "text": "green"
        },
        {
          "text": "roofs,"
        },
        {
          "text": "drawn"
        },
        {
          "text": "to"
        },
        {
          "text": "their"
        },
        {
          "text": "wide-ranging"
        },
        {
          "text": "benefits."
        },
        {
          "text": "Among"
        },
        {
          "text": "the"
        },
        {
          "text": "benefits"
        },
        {
          "text": "are"
        },
        {
          "text": "saving"
        },
        {
          "text": "on"
        },
        {
          "text": "energy"
        },
        {
          "text": "costs,"
        },
        {
          "text": "mitigating"
        },
        {
          "text": "the"
        },
        {
          "text": "risk"
        },
        {
          "text": "of"
        },
        {
          "text": "floods,"
        },
        {
          "text": "making"
        },
        {
          "text": "habitats"
        },
        {
          "text": "for"
        },
        {
          "text": "urban"
        },
        {
          "text": "wildlife,"
        },
        {
          "text": "tackling"
        },
        {
          "text": "air"
        },
        {
          "text": "pollution"
        },
        {
          "text": "and"
        },
        {
          "text": "even"
        },
        {
          "text": "growing"
        },
        {
          "text": "food."
        },
        {
          "text": "These"
        },
        {
          "text": "increasingly"
        },
        {
          "text": "radical"
        },
        {
          "text": "urban"
        },
        {
          "text": "designs"
        },
        {
          "text": "can"
        },
        {
          "text": "help"
        },
        {
          "text": "cities"
        },
        {
          "text": "adapt"
        },
        {
          "text": "to"
        },
        {
          "text": "the"
        },
        {
          "text": "monumental"
        },
        {
          "text": "problems"
        },
        {
          "text": "they"
        },
        {
          "text": "face,"
        },
        {
          "text": "such"
        },
        {
          "text": "as"
        },
        {
          "text": "access"
        },
        {
          "text": "to"
        },
        {
          "text": "resources"
        },
        {
          "text": "and"
        },
        {
          "text": "a"
        },
        {
          "text": "lack"
        },
        {
          "text": "of"
        },
        {
          "text": "green"
        },
        {
          "text": "space"
        },
        {
          "text": "due"
        },
        {
          "text": "to"
        },
        {
          "text": "development."
        },
        {
          "text": "But"
        },
        {
          "text": "the"
        },
        {
          "text": "involvement"
        },
        {
          "text": "of"
        },
        {
          "text": "city"
        },
        {
          "text": "authorities,"
        },
        {
          "text": "businesses"
        },
        {
          "text": "and"
        },
        {
          "text": "other"
        },
        {
          "text": "institutions"
        },
        {
          "text": "is"
        },
        {
          "text": "crucial"
        },
        {
          "text": "to"
        },
        {
          "text": "ensuring"
        },
        {
          "text": "their"
        },
        {
          "text": "success"
        },
        {
          "text": "–"
        },
        {
          "text": "as"
        },
        {
          "text": "is"
        },
        {
          "text": "research"
        },
        {
          "text": "investigating"
        },
        {
          "text": "different"
        },
        {
          "text": "options"
        },
        {
          "text": "to"
        },
        {
          "text": "suit"
        },
        {
          "text": "the"
        },
        {
          "text": "variety"
        },
        {
          "text": "of"
        },
        {
          "text": "rooftop"
        },
        {
          "text": "spaces"
        },
        {
          "text": "found"
        },
        {
          "text": "in"
        },
        {
          "text": "cities."
        },
        {
          "text": "The"
        },
        {
          "text": "UK"
        },
        {
          "text": "is"
        },
        {
          "text": "relatively"
        },
        {
          "text": "new"
        },
        {
          "text": "to"
        },
        {
          "text": "developing"
        },
        {
          "text": "green"
        },
        {
          "text": "roofs,"
        },
        {
          "text": "and"
        },
        {
          "text": "local"
        },
        {
          "text": "governments"
        },
        {
          "text": "and"
        },
        {
          "text": "institutions"
        },
        {
          "text": "are"
        },
        {
          "text": "playing"
        },
        {
          "text": "a"
        },
        {
          "text": "major"
        },
        {
          "text": "role"
        },
        {
          "text": "in"
        },
        {
          "text": "spreading"
        },
        {
          "text": "the"
        },
        {
          "text": "practice."
        },
        {
          "text": "London"
        },
        {
          "text": "is"
        },
        {
          "text": "home"
        },
        {
          "text": "to"
        },
        {
          "text": "much"
        },
        {
          "text": "of"
        },
        {
          "text": "the"
        },
        {
          "text": "UK’s"
        },
        {
          "text": "green"
        },
        {
          "text": "roof"
        },
        {
          "text": "market,"
        },
        {
          "text": "mainly"
        },
        {
          "text": "due"
        },
        {
          "text": "to"
        },
        {
          "text": "forward-thinking"
        },
        {
          "text": "policies"
        },
        {
          "text": "such"
        },
        {
          "text": "as"
        },
        {
          "text": "the"
        },
        {
          "text": "London"
        },
        {
          "text": "Plan,"
        },
        {
          "text": "which"
        },
        {
          "text": "has"
        },
        {
          "text": "paved"
        },
        {
          "text": "the"
        },
        {
          "text": "way"
        },
        {
          "text": "to"
        },
        {
          "text": "more"
        },
        {
          "text": "than"
        },
        {
          "text": "doubling"
        },
        {
          "text": "the"
        },
        {
          "text": "area"
        },
        {
          "text": "of"
        },
        {
          "text": "green"
        },
        {
          "text": "roofs"
        },
        {
          "text": "in"
        },
        {
          "text": "the"
        },
        {
          "text": "capital."
        },
        {
          "text": "B."
        },
        {
          "text": "Ongoing"
        },
        {
          "text": "research"
        },
        {
          "text": "is"
        },
        {
          "text": "showcasing"
        },
        {
          "text": "how"
        },
        {
          "text": "green"
        },
        {
          "text": "roofs"
        },
        {
          "text": "in"
        },
        {
          "text": "cities"
        },
        {
          "text": "can"
        },
        {
          "text": "integrate"
        },
        {
          "text": "with"
        },
        {
          "text": "‘living"
        },
        {
          "text": "walls’:"
        },
        {
          "text": "environmentally"
        },
        {
          "text": "friendly"
        },
        {
          "text": "walls"
        },
        {
          "text": "which"
        },
        {
          "text": "are"
        },
        {
          "text": "partially"
        },
        {
          "text": "or"
        },
        {
          "text": "completely"
        },
        {
          "text": "covered"
        },
        {
          "text": "with"
        },
        {
          "text": "greenery,"
        },
        {
          "text": "including"
        },
        {
          "text": "a"
        },
        {
          "text": "growing"
        },
        {
          "text": "medium,"
        },
        {
          "text": "such"
        },
        {
          "text": "as"
        },
        {
          "text": "soil"
        },
        {
          "text": "or"
        },
        {
          "text": "water."
        },
        {
          "text": "Research"
        },
        {
          "text": "also"
        },
        {
          "text": "indicates"
        },
        {
          "text": "that"
        },
        {
          "text": "green"
        },
        {
          "text": "roofs"
        },
        {
          "text": "can"
        },
        {
          "text": "be"
        },
        {
          "text": "integrated"
        },
        {
          "text": "with"
        },
        {
          "text": "drainage"
        },
        {
          "text": "systems"
        },
        {
          "text": "on"
        },
        {
          "text": "the"
        },
        {
          "text": "ground,"
        },
        {
          "text": "such"
        },
        {
          "text": "as"
        },
        {
          "text": "street"
        },
        {
          "text": "trees,"
        },
        {
          "text": "so"
        },
        {
          "text": "that"
        },
        {
          "text": "the"
        },
        {
          "text": "water"
        },
        {
          "text": "is"
        },
        {
          "text": "managed"
        },
        {
          "text": "better"
        },
        {
          "text": "and"
        },
        {
          "text": "the"
        },
        {
          "text": "built"
        },
        {
          "text": "environment"
        },
        {
          "text": "is"
        },
        {
          "text": "made"
        },
        {
          "text": "more"
        },
        {
          "text": "sustainable."
        },
        {
          "text": "There"
        },
        {
          "text": "is"
        },
        {
          "text": "also"
        },
        {
          "text": "evidence"
        },
        {
          "text": "to"
        },
        {
          "text": "demonstrate"
        },
        {
          "text": "the"
        },
        {
          "text": "social"
        },
        {
          "text": "value"
        },
        {
          "text": "of"
        },
        {
          "text": "green"
        },
        {
          "text": "roofs."
        },
        {
          "text": "Doctors"
        },
        {
          "text": "are"
        },
        {
          "text": "increasingly"
        },
        {
          "text": "prescribing"
        },
        {
          "text": "time"
        },
        {
          "text": "spent"
        },
        {
          "text": "gardening"
        },
        {
          "text": "outdoors"
        },
        {
          "text": "for"
        },
        {
          "text": "patients"
        },
        {
          "text": "dealing"
        },
        {
          "text": "with"
        },
        {
          "text": "anxiety"
        },
        {
          "text": "and"
        },
        {
          "text": "depression."
        },
        {
          "text": "And"
        },
        {
          "text": "research"
        },
        {
          "text": "has"
        },
        {
          "text": "found"
        },
        {
          "text": "that"
        },
        {
          "text": "access"
        },
        {
          "text": "to"
        },
        {
          "text": "even"
        },
        {
          "text": "the"
        },
        {
          "text": "most"
        },
        {
          "text": "basic"
        },
        {
          "text": "green"
        },
        {
          "text": "spaces"
        },
        {
          "text": "can"
        },
        {
          "text": "provide"
        },
        {
          "text": "a"
        },
        {
          "text": "better"
        },
        {
          "text": "quality"
        },
        {
          "text": "of"
        },
        {
          "text": "life"
        },
        {
          "text": "for"
        },
        {
          "text": "dementia"
        },
        {
          "text": "sufferers"
        },
        {
          "text": "and"
        },
        {
          "text": "help"
        },
        {
          "text": "people"
        },
        {
          "text": "avoid"
        },
        {
          "text": "obesity."
        },
        {
          "text": "C."
        },
        {
          "text": "In"
        },
        {
          "text": "North"
        },
        {
          "text": "America,"
        },
        {
          "text": "green"
        },
        {
          "text": "roofs"
        },
        {
          "text": "have"
        },
        {
          "text": "become"
        },
        {
          "text": "mainstream,"
        },
        {
          "text": "with"
        },
        {
          "text": "a"
        },
        {
          "text": "wide"
        },
        {
          "text": "array"
        },
        {
          "text": "of"
        },
        {
          "text": "expansive,"
        },
        {
          "text": "accessible"
        },
        {
          "text": "and"
        },
        {
          "text": "food-producing"
        },
        {
          "text": "roofs"
        },
        {
          "text": "installed"
        },
        {
          "text": "in"
        },
        {
          "text": "buildings."
        },
        {
          "text": "Again,"
        },
        {
          "text": "city"
        },
        {
          "text": "leaders"
        },
        {
          "text": "and"
        },
        {
          "text": "authorities"
        },
        {
          "text": "have"
        },
        {
          "text": "helped"
        },
        {
          "text": "push"
        },
        {
          "text": "the"
        },
        {
          "text": "movement"
        },
        {
          "text": "forward"
        },
        {
          "text": "–"
        },
        {
          "text": "only"
        },
        {
          "text": "recently,"
        },
        {
          "text": "San"
        },
        {
          "text": "Francisco,"
        },
        {
          "text": "USA,"
        },
        {
          "text": "created"
        },
        {
          "text": "a"
        },
        {
          "text": "policy"
        },
        {
          "text": "requiring"
        },
        {
          "text": "new"
        },
        {
          "text": "buildings"
        },
        {
          "text": "to"
        },
        {
          "text": "have"
        },
        {
          "text": "green"
        },
        {
          "text": "roofs."
        },
        {
          "text": "Toronto,"
        },
        {
          "text": "Canada,"
        },
        {
          "text": "has"
        },
        {
          "text": "policies"
        },
        {
          "text": "dating"
        },
        {
          "text": "from"
        },
        {
          "text": "the"
        },
        {
          "text": "1990s,"
        },
        {
          "text": "encouraging"
        },
        {
          "text": "the"
        },
        {
          "text": "development"
        },
        {
          "text": "of"
        },
        {
          "text": "urban"
        },
        {
          "text": "farms"
        },
        {
          "text": "on"
        },
        {
          "text": "rooftops."
        },
        {
          "text": "These"
        },
        {
          "text": "countries"
        },
        {
          "text": "also"
        },
        {
          "text": "benefit"
        },
        {
          "text": "from"
        },
        {
          "text": "having"
        },
        {
          "text": "newer"
        },
        {
          "text": "buildings"
        },
        {
          "text": "than"
        },
        {
          "text": "in"
        },
        {
          "text": "many"
        },
        {
          "text": "parts"
        },
        {
          "text": "of"
        },
        {
          "text": "the"
        },
        {
          "text": "world,"
        },
        {
          "text": "which"
        },
        {
          "text": "makes"
        },
        {
          "text": "it"
        },
        {
          "text": "easier"
        },
        {
          "text": "to"
        },
        {
          "text": "install"
        },
        {
          "text": "green"
        },
        {
          "text": "roofs."
        },
        {
          "text": "Being"
        },
        {
          "text": "able"
        },
        {
          "text": "to"
        },
        {
          "text": "keep"
        },
        {
          "text": "enough"
        },
        {
          "text": "water"
        },
        {
          "text": "at"
        },
        {
          "text": "roof"
        },
        {
          "text": "height"
        },
        {
          "text": "and"
        },
        {
          "text": "distribute"
        },
        {
          "text": "it"
        },
        {
          "text": "right"
        },
        {
          "text": "across"
        },
        {
          "text": "the"
        },
        {
          "text": "rooftop"
        },
        {
          "text": "is"
        },
        {
          "text": "crucial"
        },
        {
          "text": "to"
        },
        {
          "text": "maintaining"
        },
        {
          "text": "the"
        },
        {
          "text": "plants"
        },
        {
          "text": "on"
        },
        {
          "text": "any"
        },
        {
          "text": "green"
        },
        {
          "text": "roof"
        },
        {
          "text": "–"
        },
        {
          "text": "especially"
        },
        {
          "text": "on"
        },
        {
          "text": "‘edible"
        },
        {
          "text": "roofs’"
        },
        {
          "text": "where"
        },
        {
          "text": "fruit"
        },
        {
          "text": "and"
        },
        {
          "text": "vegetables"
        },
        {
          "text": "are"
        },
        {
          "text": "farmed."
        },
        {
          "text": "And"
        },
        {
          "text": "it’s"
        },
        {
          "text": "much"
        },
        {
          "text": "easier"
        },
        {
          "text": "to"
        },
        {
          "text": "do"
        },
        {
          "text": "this"
        },
        {
          "text": "in"
        },
        {
          "text": "newer"
        },
        {
          "text": "buildings,"
        },
        {
          "text": "which"
        },
        {
          "text": "can"
        },
        {
          "text": "typically"
        },
        {
          "text": "hold"
        },
        {
          "text": "greater"
        },
        {
          "text": "weight,"
        },
        {
          "text": "than"
        },
        {
          "text": "to"
        },
        {
          "text": "retro-fit"
        },
        {
          "text": "old"
        },
        {
          "text": "ones."
        },
        {
          "text": "Having"
        },
        {
          "text": "a"
        },
        {
          "text": "stronger"
        },
        {
          "text": "roof"
        },
        {
          "text": "also"
        },
        {
          "text": "makes"
        },
        {
          "text": "it"
        },
        {
          "text": "easier"
        },
        {
          "text": "to"
        },
        {
          "text": "grow"
        },
        {
          "text": "a"
        },
        {
          "text": "greater"
        },
        {
          "text": "variety"
        },
        {
          "text": "of"
        },
        {
          "text": "plants,"
        },
        {
          "text": "since"
        },
        {
          "text": "the"
        },
        {
          "text": "soil"
        },
        {
          "text": "can"
        },
        {
          "text": "be"
        },
        {
          "text": "deeper."
        },
        {
          "text": "D."
        },
        {
          "text": "For"
        },
        {
          "text": "green"
        },
        {
          "text": "roofs"
        },
        {
          "text": "to"
        },
        {
          "text": "become"
        },
        {
          "text": "the"
        },
        {
          "text": "norm"
        },
        {
          "text": "for"
        },
        {
          "text": "new"
        },
        {
          "text": "developments,"
        },
        {
          "text": "there"
        },
        {
          "text": "needs"
        },
        {
          "text": "to"
        },
        {
          "text": "be"
        },
        {
          "text": "support"
        },
        {
          "text": "from"
        },
        {
          "text": "public"
        },
        {
          "text": "authorities"
        },
        {
          "text": "and"
        },
        {
          "text": "private"
        },
        {
          "text": "investors."
        },
        {
          "text": "Those"
        },
        {
          "text": "responsible"
        },
        {
          "text": "for"
        },
        {
          "text": "maintaining"
        },
        {
          "text": "buildings"
        },
        {
          "text": "may"
        },
        {
          "text": "have"
        },
        {
          "text": "to"
        },
        {
          "text": "acquire"
        },
        {
          "text": "new"
        },
        {
          "text": "skills,"
        },
        {
          "text": "such"
        },
        {
          "text": "as"
        },
        {
          "text": "landscaping,"
        },
        {
          "text": "and"
        },
        {
          "text": "in"
        },
        {
          "text": "some"
        },
        {
          "text": "cases,"
        },
        {
          "text": "volunteers"
        },
        {
          "text": "may"
        },
        {
          "text": "be"
        },
        {
          "text": "needed"
        },
        {
          "text": "to"
        },
        {
          "text": "help"
        },
        {
          "text": "out."
        },
        {
          "text": "Other"
        },
        {
          "text": "considerations"
        },
        {
          "text": "include"
        },
        {
          "text": "installing"
        },
        {
          "text": "drainage"
        },
        {
          "text": "paths,"
        },
        {
          "text": "meeting"
        },
        {
          "text": "health"
        },
        {
          "text": "and"
        },
        {
          "text": "safety"
        },
        {
          "text": "requirements"
        },
        {
          "text": "and"
        },
        {
          "text": "perhaps"
        },
        {
          "text": "allowing"
        },
        {
          "text": "access"
        },
        {
          "text": "for"
        },
        {
          "text": "the"
        },
        {
          "text": "public,"
        },
        {
          "text": "as"
        },
        {
          "text": "well"
        },
        {
          "text": "as"
        },
        {
          "text": "planning"
        },
        {
          "text": "restrictions"
        },
        {
          "text": "and"
        },
        {
          "text": "disruption"
        },
        {
          "text": "from"
        },
        {
          "text": "regular"
        },
        {
          "text": "activities"
        },
        {
          "text": "in"
        },
        {
          "text": "and"
        },
        {
          "text": "around"
        },
        {
          "text": "the"
        },
        {
          "text": "buildings"
        },
        {
          "text": "during"
        },
        {
          "text": "installation."
        },
        {
          "text": "To"
        },
        {
          "text": "convince"
        },
        {
          "text": "investors"
        },
        {
          "text": "and"
        },
        {
          "text": "developers"
        },
        {
          "text": "that"
        },
        {
          "text": "installing"
        },
        {
          "text": "green"
        },
        {
          "text": "roofs"
        },
        {
          "text": "is"
        },
        {
          "text": "worthwhile,"
        },
        {
          "text": "economic"
        },
        {
          "text": "arguments"
        },
        {
          "text": "are"
        },
        {
          "text": "still"
        },
        {
          "text": "the"
        },
        {
          "text": "most"
        },
        {
          "text": "important."
        },
        {
          "text": "The"
        },
        {
          "text": "term"
        },
        {
          "text": "‘natural"
        },
        {
          "text": "capital’"
        },
        {
          "text": "has"
        },
        {
          "text": "been"
        },
        {
          "text": "developed"
        },
        {
          "text": "to"
        },
        {
          "text": "explain"
        },
        {
          "text": "the"
        },
        {
          "text": "economic"
        },
        {
          "text": "value"
        },
        {
          "text": "of"
        },
        {
          "text": "nature;"
        },
        {
          "text": "for"
        },
        {
          "text": "example,"
        },
        {
          "text": "measuring"
        },
        {
          "text": "the"
        },
        {
          "text": "money"
        },
        {
          "text": "saved"
        },
        {
          "text": "by"
        },
        {
          "text": "installing"
        },
        {
          "text": "natural"
        },
        {
          "text": "solutions"
        },
        {
          "text": "to"
        },
        {
          "text": "protect"
        },
        {
          "text": "against"
        },
        {
          "text": "flood"
        },
        {
          "text": "damage,"
        },
        {
          "text": "adapt"
        },
        {
          "text": "to"
        },
        {
          "text": "climate"
        },
        {
          "text": "change"
        },
        {
          "text": "or"
        },
        {
          "text": "help"
        },
        {
          "text": "people"
        },
        {
          "text": "lead"
        },
        {
          "text": "healthier"
        },
        {
          "text": "and"
        },
        {
          "text": "happier"
        },
        {
          "text": "lives."
        },
        {
          "text": "E."
        },
        {
          "text": "As"
        },
        {
          "text": "the"
        },
        {
          "text": "expertise"
        },
        {
          "text": "about"
        },
        {
          "text": "green"
        },
        {
          "text": "roofs"
        },
        {
          "text": "grows,"
        },
        {
          "text": "official"
        },
        {
          "text": "standards"
        },
        {
          "text": "have"
        },
        {
          "text": "been"
        },
        {
          "text": "developed"
        },
        {
          "text": "to"
        },
        {
          "text": "ensure"
        },
        {
          "text": "that"
        },
        {
          "text": "they"
        },
        {
          "text": "are"
        },
        {
          "text": "designed,"
        },
        {
          "text": "constructed"
        },
        {
          "text": "and"
        },
        {
          "text": "maintained"
        },
        {
          "text": "properly,"
        },
        {
          "text": "and"
        },
        {
          "text": "function"
        },
        {
          "text": "well."
        },
        {
          "text": "Improvements"
        },
        {
          "text": "in"
        },
        {
          "text": "the"
        },
        {
          "text": "science"
        },
        {
          "text": "and"
        },
        {
          "text": "technology"
        },
        {
          "text": "underpinning"
        },
        {
          "text": "green"
        },
        {
          "text": "roof"
        },
        {
          "text": "development"
        },
        {
          "text": "have"
        },
        {
          "text": "also"
        },
        {
          "text": "led"
        },
        {
          "text": "to"
        },
        {
          "text": "new"
        },
        {
          "text": "variations"
        },
        {
          "text": "in"
        },
        {
          "text": "the"
        },
        {
          "text": "concept."
        },
        {
          "text": "For"
        },
        {
          "text": "example,"
        },
        {
          "text": "‘blue"
        },
        {
          "text": "roofs’"
        },
        {
          "text": "enable"
        },
        {
          "text": "buildings"
        },
        {
          "text": "to"
        },
        {
          "text": "hold"
        },
        {
          "text": "water"
        },
        {
          "text": "over"
        },
        {
          "text": "longer"
        },
        {
          "text": "periods"
        },
        {
          "text": "of"
        },
        {
          "text": "time,"
        },
        {
          "text": "rather"
        },
        {
          "text": "than"
        },
        {
          "text": "draining"
        },
        {
          "text": "it"
        },
        {
          "text": "away"
        },
        {
          "text": "quickly"
        },
        {
          "text": "–"
        },
        {
          "text": "crucial"
        },
        {
          "text": "in"
        },
        {
          "text": "times"
        },
        {
          "text": "of"
        },
        {
          "text": "heavier"
        },
        {
          "text": "rainfall."
        },
        {
          "text": "There"
        },
        {
          "text": "are"
        },
        {
          "text": "also"
        },
        {
          "text": "combinations"
        },
        {
          "text": "of"
        },
        {
          "text": "green"
        },
        {
          "text": "roofs"
        },
        {
          "text": "with"
        },
        {
          "text": "solar"
        },
        {
          "text": "panels,"
        },
        {
          "text": "and"
        },
        {
          "text": "‘brown"
        },
        {
          "text": "roofs’"
        },
        {
          "text": "which"
        },
        {
          "text": "are"
        },
        {
          "text": "wilder"
        },
        {
          "text": "in"
        },
        {
          "text": "nature"
        },
        {
          "text": "and"
        },
        {
          "text": "maximise"
        },
        {
          "text": "biodiversity."
        },
        {
          "text": "If"
        },
        {
          "text": "the"
        },
        {
          "text": "trend"
        },
        {
          "text": "continues,"
        },
        {
          "text": "it"
        },
        {
          "text": "could"
        },
        {
          "text": "create"
        },
        {
          "text": "new"
        },
        {
          "text": "jobs"
        },
        {
          "text": "and"
        },
        {
          "text": "a"
        },
        {
          "text": "more"
        },
        {
          "text": "vibrant"
        },
        {
          "text": "and"
        },
        {
          "text": "sustainable"
        },
        {
          "text": "local"
        },
        {
          "text": "food"
        },
        {
          "text": "economy"
        },
        {
          "text": "–"
        },
        {
          "text": "alongside"
        },
        {
          "text": "many"
        },
        {
          "text": "other"
        },
        {
          "text": "benefits."
        },
        {
          "text": "There"
        },
        {
          "text": "are"
        },
        {
          "text": "still"
        },
        {
          "text": "barriers"
        },
        {
          "text": "to"
        },
        {
          "text": "overcome,"
        },
        {
          "text": "but"
        },
        {
          "text": "the"
        },
        {
          "text": "evidence"
        },
        {
          "text": "so"
        },
        {
          "text": "far"
        },
        {
          "text": "indicates"
        },
        {
          "text": "that"
        },
        {
          "text": "green"
        },
        {
          "text": "roofs"
        },
        {
          "text": "have"
        },
        {
          "text": "the"
        },
        {
          "text": "potential"
        },
        {
          "text": "to"
        },
        {
          "text": "transform"
        },
        {
          "text": "cities"
        },
        {
          "text": "and"
        },
        {
          "text": "help"
        },
        {
          "text": "them"
        },
        {
          "text": "function"
        },
        {
          "text": "sustainably"
        },
        {
          "text": "long"
        },
        {
          "text": "into"
        },
        {
          "text": "the"
        },
        {
          "text": "future."
        },
        {
          "text": "The"
        },
        {
          "text": "success"
        },
        {
          "text": "stories"
        },
        {
          "text": "need"
        },
        {
          "text": "to"
        },
        {
          "text": "be"
        },
        {
          "text": "studied"
        },
        {
          "text": "and"
        },
        {
          "text": "replicated"
        },
        {
          "text": "elsewhere,"
        },
        {
          "text": "to"
        },
        {
          "text": "make"
        },
        {
          "text": "green,"
        },
        {
          "text": "blue,"
        },
        {
          "text": "brown"
        },
        {
          "text": "and"
        },
        {
          "text": "food-producing"
        },
        {
          "text": "roofs"
        },
        {
          "text": "the"
        },
        {
          "text": "norm"
        },
        {
          "text": "in"
        },
        {
          "text": "cities"
        },
        {
          "text": "around"
        },
        {
          "text": "the"
        },
        {
          "text": "world."
        }
      ],
      "questionGroups": []
    }
  ]
}