{
  "version": 1,
  "title": "PASSAGE_P14_C12",
  "durationMinutes": 60,
  "examTrack": "ielts",
  "parts": [
    {
      "partNumber": 1,
      "rangeLabel": "",
      "passageTitle": "When evolution runs backwards",
      "passage": [
        {
          "text": "When"
        },
        {
          "text": "evolution"
        },
        {
          "text": "runs"
        },
        {
          "text": "backwards"
        },
        {
          "text": "Evolution"
        },
        {
          "text": "isn’t"
        },
        {
          "text": "supposed"
        },
        {
          "text": "to"
        },
        {
          "text": "run"
        },
        {
          "text": "backwards"
        },
        {
          "text": "–"
        },
        {
          "text": "yet"
        },
        {
          "text": "an"
        },
        {
          "text": "increasing"
        },
        {
          "text": "number"
        },
        {
          "text": "of"
        },
        {
          "text": "examples"
        },
        {
          "text": "show"
        },
        {
          "text": "that"
        },
        {
          "text": "it"
        },
        {
          "text": "does"
        },
        {
          "text": "and"
        },
        {
          "text": "that"
        },
        {
          "text": "it"
        },
        {
          "text": "can"
        },
        {
          "text": "sometimes"
        },
        {
          "text": "represent"
        },
        {
          "text": "the"
        },
        {
          "text": "future"
        },
        {
          "text": "of"
        },
        {
          "text": "a"
        },
        {
          "text": "species."
        },
        {
          "text": "The"
        },
        {
          "text": "description"
        },
        {
          "text": "of"
        },
        {
          "text": "any"
        },
        {
          "text": "animal"
        },
        {
          "text": "as"
        },
        {
          "text": "an"
        },
        {
          "text": "‘evolutionary"
        },
        {
          "text": "throwback’"
        },
        {
          "text": "is"
        },
        {
          "text": "controversial."
        },
        {
          "text": "For"
        },
        {
          "text": "the"
        },
        {
          "text": "better"
        },
        {
          "text": "part"
        },
        {
          "text": "of"
        },
        {
          "text": "a"
        },
        {
          "text": "century,"
        },
        {
          "text": "most"
        },
        {
          "text": "biologists"
        },
        {
          "text": "have"
        },
        {
          "text": "been"
        },
        {
          "text": "reluctant"
        },
        {
          "text": "to"
        },
        {
          "text": "use"
        },
        {
          "text": "those"
        },
        {
          "text": "words,"
        },
        {
          "text": "mindful"
        },
        {
          "text": "of"
        },
        {
          "text": "a"
        },
        {
          "text": "principle"
        },
        {
          "text": "of"
        },
        {
          "text": "evolution"
        },
        {
          "text": "that"
        },
        {
          "text": "says"
        },
        {
          "text": "‘evolution"
        },
        {
          "text": "cannot"
        },
        {
          "text": "run"
        },
        {
          "text": "backwards."
        },
        {
          "text": "But"
        },
        {
          "text": "as"
        },
        {
          "text": "more"
        },
        {
          "text": "and"
        },
        {
          "text": "more"
        },
        {
          "text": "examples"
        },
        {
          "text": "come"
        },
        {
          "text": "to"
        },
        {
          "text": "light"
        },
        {
          "text": "and"
        },
        {
          "text": "modern"
        },
        {
          "text": "genetics"
        },
        {
          "text": "enters"
        },
        {
          "text": "the"
        },
        {
          "text": "scene,"
        },
        {
          "text": "that"
        },
        {
          "text": "principle"
        },
        {
          "text": "is"
        },
        {
          "text": "having"
        },
        {
          "text": "to"
        },
        {
          "text": "be"
        },
        {
          "text": "rewritten."
        },
        {
          "text": "Not"
        },
        {
          "text": "only"
        },
        {
          "text": "are"
        },
        {
          "text": "evolutionary"
        },
        {
          "text": "throwbacks"
        },
        {
          "text": "possible,"
        },
        {
          "text": "they"
        },
        {
          "text": "sometimes"
        },
        {
          "text": "play"
        },
        {
          "text": "an"
        },
        {
          "text": "important"
        },
        {
          "text": "role"
        },
        {
          "text": "in"
        },
        {
          "text": "the"
        },
        {
          "text": "forward"
        },
        {
          "text": "march"
        },
        {
          "text": "of"
        },
        {
          "text": "evolution."
        },
        {
          "text": "The"
        },
        {
          "text": "technical"
        },
        {
          "text": "term"
        },
        {
          "text": "for"
        },
        {
          "text": "an"
        },
        {
          "text": "evolutionary"
        },
        {
          "text": "throwback"
        },
        {
          "text": "is"
        },
        {
          "text": "an"
        },
        {
          "text": "‘atavism’,"
        },
        {
          "text": "from"
        },
        {
          "text": "the"
        },
        {
          "text": "Latin"
        },
        {
          "text": "atavus,"
        },
        {
          "text": "meaning"
        },
        {
          "text": "forefather."
        },
        {
          "text": "The"
        },
        {
          "text": "word"
        },
        {
          "text": "has"
        },
        {
          "text": "ugly"
        },
        {
          "text": "connotations"
        },
        {
          "text": "thanks"
        },
        {
          "text": "largely"
        },
        {
          "text": "to"
        },
        {
          "text": "Cesare"
        },
        {
          "text": "Lombroso,"
        },
        {
          "text": "a"
        },
        {
          "text": "19th-century"
        },
        {
          "text": "Italian"
        },
        {
          "text": "medic"
        },
        {
          "text": "who"
        },
        {
          "text": "argued"
        },
        {
          "text": "that"
        },
        {
          "text": "criminals"
        },
        {
          "text": "were"
        },
        {
          "text": "born"
        },
        {
          "text": "not"
        },
        {
          "text": "made"
        },
        {
          "text": "and"
        },
        {
          "text": "could"
        },
        {
          "text": "be"
        },
        {
          "text": "identified"
        },
        {
          "text": "by"
        },
        {
          "text": "certain"
        },
        {
          "text": "physical"
        },
        {
          "text": "features"
        },
        {
          "text": "that"
        },
        {
          "text": "were"
        },
        {
          "text": "throwbacks"
        },
        {
          "text": "to"
        },
        {
          "text": "a"
        },
        {
          "text": "primitive,"
        },
        {
          "text": "sub-human"
        },
        {
          "text": "state."
        },
        {
          "text": "While"
        },
        {
          "text": "Lombroso"
        },
        {
          "text": "was"
        },
        {
          "text": "measuring"
        },
        {
          "text": "criminals,"
        },
        {
          "text": "a"
        },
        {
          "text": "Belgian"
        },
        {
          "text": "palaeontologist"
        },
        {
          "text": "called"
        },
        {
          "text": "Louis"
        },
        {
          "text": "Dollo"
        },
        {
          "text": "was"
        },
        {
          "text": "studying"
        },
        {
          "text": "fossil"
        },
        {
          "text": "records"
        },
        {
          "text": "and"
        },
        {
          "text": "coming"
        },
        {
          "text": "to"
        },
        {
          "text": "the"
        },
        {
          "text": "opposite"
        },
        {
          "text": "conclusion."
        },
        {
          "text": "In"
        },
        {
          "text": "1890"
        },
        {
          "text": "he"
        },
        {
          "text": "proposed"
        },
        {
          "text": "that"
        },
        {
          "text": "evolution"
        },
        {
          "text": "was"
        },
        {
          "text": "irreversible:"
        },
        {
          "text": "that"
        },
        {
          "text": "‘an"
        },
        {
          "text": "organism"
        },
        {
          "text": "is"
        },
        {
          "text": "unable"
        },
        {
          "text": "to"
        },
        {
          "text": "return,"
        },
        {
          "text": "even"
        },
        {
          "text": "partially,"
        },
        {
          "text": "to"
        },
        {
          "text": "a"
        },
        {
          "text": "previous"
        },
        {
          "text": "stage"
        },
        {
          "text": "already"
        },
        {
          "text": "realised"
        },
        {
          "text": "in"
        },
        {
          "text": "the"
        },
        {
          "text": "ranks"
        },
        {
          "text": "of"
        },
        {
          "text": "its"
        },
        {
          "text": "ancestors."
        },
        {
          "text": "Early"
        },
        {
          "text": "20th-century"
        },
        {
          "text": "biologists"
        },
        {
          "text": "came"
        },
        {
          "text": "to"
        },
        {
          "text": "a"
        },
        {
          "text": "similar"
        },
        {
          "text": "conclusion,"
        },
        {
          "text": "though"
        },
        {
          "text": "they"
        },
        {
          "text": "qualified"
        },
        {
          "text": "it"
        },
        {
          "text": "in"
        },
        {
          "text": "terms"
        },
        {
          "text": "of"
        },
        {
          "text": "probability,"
        },
        {
          "text": "stating"
        },
        {
          "text": "that"
        },
        {
          "text": "there"
        },
        {
          "text": "is"
        },
        {
          "text": "no"
        },
        {
          "text": "reason"
        },
        {
          "text": "why"
        },
        {
          "text": "evolution"
        },
        {
          "text": "cannot"
        },
        {
          "text": "run"
        },
        {
          "text": "backwards"
        },
        {
          "text": "-it"
        },
        {
          "text": "is"
        },
        {
          "text": "just"
        },
        {
          "text": "very"
        },
        {
          "text": "unlikely."
        },
        {
          "text": "And"
        },
        {
          "text": "so"
        },
        {
          "text": "the"
        },
        {
          "text": "idea"
        },
        {
          "text": "of"
        },
        {
          "text": "irreversibility"
        },
        {
          "text": "in"
        },
        {
          "text": "evolution"
        },
        {
          "text": "stuck"
        },
        {
          "text": "and"
        },
        {
          "text": "came"
        },
        {
          "text": "to"
        },
        {
          "text": "be"
        },
        {
          "text": "known"
        },
        {
          "text": "as"
        },
        {
          "text": "‘Dollo’s"
        },
        {
          "text": "law."
        },
        {
          "text": "If"
        },
        {
          "text": "Dollo’s"
        },
        {
          "text": "law"
        },
        {
          "text": "is"
        },
        {
          "text": "right,"
        },
        {
          "text": "atavisms"
        },
        {
          "text": "should"
        },
        {
          "text": "occur"
        },
        {
          "text": "only"
        },
        {
          "text": "very"
        },
        {
          "text": "rarely,"
        },
        {
          "text": "if"
        },
        {
          "text": "at"
        },
        {
          "text": "all."
        },
        {
          "text": "Yet"
        },
        {
          "text": "almost"
        },
        {
          "text": "since"
        },
        {
          "text": "the"
        },
        {
          "text": "idea"
        },
        {
          "text": "took"
        },
        {
          "text": "root,"
        },
        {
          "text": "exceptions"
        },
        {
          "text": "have"
        },
        {
          "text": "been"
        },
        {
          "text": "cropping"
        },
        {
          "text": "up."
        },
        {
          "text": "In"
        },
        {
          "text": "1919,"
        },
        {
          "text": "for"
        },
        {
          "text": "example,"
        },
        {
          "text": "a"
        },
        {
          "text": "humpback"
        },
        {
          "text": "whale"
        },
        {
          "text": "with"
        },
        {
          "text": "a"
        },
        {
          "text": "pair"
        },
        {
          "text": "of"
        },
        {
          "text": "leglike"
        },
        {
          "text": "appendages"
        },
        {
          "text": "over"
        },
        {
          "text": "a"
        },
        {
          "text": "metre"
        },
        {
          "text": "long,"
        },
        {
          "text": "complete"
        },
        {
          "text": "with"
        },
        {
          "text": "a"
        },
        {
          "text": "full"
        },
        {
          "text": "set"
        },
        {
          "text": "of"
        },
        {
          "text": "limb"
        },
        {
          "text": "bones,"
        },
        {
          "text": "was"
        },
        {
          "text": "caught"
        },
        {
          "text": "off"
        },
        {
          "text": "Vancouver"
        },
        {
          "text": "Island"
        },
        {
          "text": "in"
        },
        {
          "text": "Canada."
        },
        {
          "text": "Explorer"
        },
        {
          "text": "Roy"
        },
        {
          "text": "Chapman"
        },
        {
          "text": "Andrews"
        },
        {
          "text": "argued"
        },
        {
          "text": "at"
        },
        {
          "text": "the"
        },
        {
          "text": "time"
        },
        {
          "text": "that"
        },
        {
          "text": "the"
        },
        {
          "text": "whale"
        },
        {
          "text": "must"
        },
        {
          "text": "be"
        },
        {
          "text": "a"
        },
        {
          "text": "throwback"
        },
        {
          "text": "to"
        },
        {
          "text": "a"
        },
        {
          "text": "land-living"
        },
        {
          "text": "ancestor."
        },
        {
          "text": "‘I"
        },
        {
          "text": "can"
        },
        {
          "text": "see"
        },
        {
          "text": "no"
        },
        {
          "text": "other"
        },
        {
          "text": "explanation,’"
        },
        {
          "text": "he"
        },
        {
          "text": "wrote"
        },
        {
          "text": "in"
        },
        {
          "text": "1921."
        },
        {
          "text": "Since"
        },
        {
          "text": "then,"
        },
        {
          "text": "so"
        },
        {
          "text": "many"
        },
        {
          "text": "other"
        },
        {
          "text": "examples"
        },
        {
          "text": "have"
        },
        {
          "text": "been"
        },
        {
          "text": "discovered"
        },
        {
          "text": "that"
        },
        {
          "text": "it"
        },
        {
          "text": "no"
        },
        {
          "text": "longer"
        },
        {
          "text": "makes"
        },
        {
          "text": "sense"
        },
        {
          "text": "to"
        },
        {
          "text": "say"
        },
        {
          "text": "that"
        },
        {
          "text": "evolution"
        },
        {
          "text": "is"
        },
        {
          "text": "as"
        },
        {
          "text": "good"
        },
        {
          "text": "as"
        },
        {
          "text": "irreversible."
        },
        {
          "text": "And"
        },
        {
          "text": "this"
        },
        {
          "text": "poses"
        },
        {
          "text": "a"
        },
        {
          "text": "puzzle:"
        },
        {
          "text": "how"
        },
        {
          "text": "can"
        },
        {
          "text": "characteristics"
        },
        {
          "text": "that"
        },
        {
          "text": "disappeared"
        },
        {
          "text": "millions"
        },
        {
          "text": "of"
        },
        {
          "text": "years"
        },
        {
          "text": "ago"
        },
        {
          "text": "suddenly"
        },
        {
          "text": "reappear?"
        },
        {
          "text": "In"
        },
        {
          "text": "1994,"
        },
        {
          "text": "Rudolf"
        },
        {
          "text": "Raff"
        },
        {
          "text": "and"
        },
        {
          "text": "colleagues"
        },
        {
          "text": "at"
        },
        {
          "text": "Indiana"
        },
        {
          "text": "University"
        },
        {
          "text": "in"
        },
        {
          "text": "the"
        },
        {
          "text": "USA"
        },
        {
          "text": "decided"
        },
        {
          "text": "to"
        },
        {
          "text": "use"
        },
        {
          "text": "genetics"
        },
        {
          "text": "to"
        },
        {
          "text": "put"
        },
        {
          "text": "a"
        },
        {
          "text": "number"
        },
        {
          "text": "on"
        },
        {
          "text": "the"
        },
        {
          "text": "probability"
        },
        {
          "text": "of"
        },
        {
          "text": "evolution"
        },
        {
          "text": "going"
        },
        {
          "text": "into"
        },
        {
          "text": "reverse."
        },
        {
          "text": "They"
        },
        {
          "text": "reasoned"
        },
        {
          "text": "that"
        },
        {
          "text": "while"
        },
        {
          "text": "some"
        },
        {
          "text": "evolutionary"
        },
        {
          "text": "changes"
        },
        {
          "text": "involve"
        },
        {
          "text": "the"
        },
        {
          "text": "loss"
        },
        {
          "text": "of"
        },
        {
          "text": "genes"
        },
        {
          "text": "and"
        },
        {
          "text": "are"
        },
        {
          "text": "therefore"
        },
        {
          "text": "irreversible,"
        },
        {
          "text": "others"
        },
        {
          "text": "may"
        },
        {
          "text": "be"
        },
        {
          "text": "the"
        },
        {
          "text": "result"
        },
        {
          "text": "of"
        },
        {
          "text": "genes"
        },
        {
          "text": "being"
        },
        {
          "text": "switched"
        },
        {
          "text": "off."
        },
        {
          "text": "If"
        },
        {
          "text": "these"
        },
        {
          "text": "silent"
        },
        {
          "text": "genes"
        },
        {
          "text": "are"
        },
        {
          "text": "somehow"
        },
        {
          "text": "switched"
        },
        {
          "text": "back"
        },
        {
          "text": "on,"
        },
        {
          "text": "they"
        },
        {
          "text": "argued,"
        },
        {
          "text": "long-lost"
        },
        {
          "text": "traits"
        },
        {
          "text": "could"
        },
        {
          "text": "reappear."
        },
        {
          "text": "Raff’s"
        },
        {
          "text": "team"
        },
        {
          "text": "went"
        },
        {
          "text": "on"
        },
        {
          "text": "to"
        },
        {
          "text": "calculate"
        },
        {
          "text": "the"
        },
        {
          "text": "likelihood"
        },
        {
          "text": "of"
        },
        {
          "text": "it"
        },
        {
          "text": "happening."
        },
        {
          "text": "Silent"
        },
        {
          "text": "genes"
        },
        {
          "text": "accumulate"
        },
        {
          "text": "random"
        },
        {
          "text": "mutations,"
        },
        {
          "text": "they"
        },
        {
          "text": "reasoned,"
        },
        {
          "text": "eventually"
        },
        {
          "text": "rendering"
        },
        {
          "text": "them"
        },
        {
          "text": "useless."
        },
        {
          "text": "So"
        },
        {
          "text": "how"
        },
        {
          "text": "long"
        },
        {
          "text": "can"
        },
        {
          "text": "a"
        },
        {
          "text": "gene"
        },
        {
          "text": "survive"
        },
        {
          "text": "in"
        },
        {
          "text": "a"
        },
        {
          "text": "species"
        },
        {
          "text": "if"
        },
        {
          "text": "it"
        },
        {
          "text": "is"
        },
        {
          "text": "no"
        },
        {
          "text": "longer"
        },
        {
          "text": "used?"
        },
        {
          "text": "The"
        },
        {
          "text": "team"
        },
        {
          "text": "calculated"
        },
        {
          "text": "that"
        },
        {
          "text": "there"
        },
        {
          "text": "is"
        },
        {
          "text": "a"
        },
        {
          "text": "good"
        },
        {
          "text": "chance"
        },
        {
          "text": "of"
        },
        {
          "text": "silent"
        },
        {
          "text": "genes"
        },
        {
          "text": "surviving"
        },
        {
          "text": "for"
        },
        {
          "text": "up"
        },
        {
          "text": "to"
        },
        {
          "text": "6"
        },
        {
          "text": "million"
        },
        {
          "text": "years"
        },
        {
          "text": "in"
        },
        {
          "text": "at"
        },
        {
          "text": "least"
        },
        {
          "text": "a"
        },
        {
          "text": "few"
        },
        {
          "text": "individuals"
        },
        {
          "text": "in"
        },
        {
          "text": "a"
        },
        {
          "text": "population,"
        },
        {
          "text": "and"
        },
        {
          "text": "that"
        },
        {
          "text": "some"
        },
        {
          "text": "might"
        },
        {
          "text": "survive"
        },
        {
          "text": "as"
        },
        {
          "text": "long"
        },
        {
          "text": "as"
        },
        {
          "text": "10"
        },
        {
          "text": "million"
        },
        {
          "text": "years."
        },
        {
          "text": "In"
        },
        {
          "text": "other"
        },
        {
          "text": "words,"
        },
        {
          "text": "throwbacks"
        },
        {
          "text": "are"
        },
        {
          "text": "possible,"
        },
        {
          "text": "but"
        },
        {
          "text": "only"
        },
        {
          "text": "to"
        },
        {
          "text": "the"
        },
        {
          "text": "relatively"
        },
        {
          "text": "recent"
        },
        {
          "text": "evolutionary"
        },
        {
          "text": "past."
        },
        {
          "text": "As"
        },
        {
          "text": "a"
        },
        {
          "text": "possible"
        },
        {
          "text": "example,"
        },
        {
          "text": "the"
        },
        {
          "text": "team"
        },
        {
          "text": "pointed"
        },
        {
          "text": "to"
        },
        {
          "text": "the"
        },
        {
          "text": "mole"
        },
        {
          "text": "salamanders"
        },
        {
          "text": "of"
        },
        {
          "text": "Mexico"
        },
        {
          "text": "and"
        },
        {
          "text": "California."
        },
        {
          "text": "Like"
        },
        {
          "text": "most"
        },
        {
          "text": "amphibians"
        },
        {
          "text": "these"
        },
        {
          "text": "begin"
        },
        {
          "text": "life"
        },
        {
          "text": "in"
        },
        {
          "text": "a"
        },
        {
          "text": "juvenile"
        },
        {
          "text": "‘tadpole’"
        },
        {
          "text": "state,"
        },
        {
          "text": "then"
        },
        {
          "text": "metamorphose"
        },
        {
          "text": "into"
        },
        {
          "text": "the"
        },
        {
          "text": "adult"
        },
        {
          "text": "form"
        },
        {
          "text": "–"
        },
        {
          "text": "except"
        },
        {
          "text": "for"
        },
        {
          "text": "one"
        },
        {
          "text": "species,"
        },
        {
          "text": "the"
        },
        {
          "text": "axolotl,"
        },
        {
          "text": "which"
        },
        {
          "text": "famously"
        },
        {
          "text": "lives"
        },
        {
          "text": "its"
        },
        {
          "text": "entire"
        },
        {
          "text": "life"
        },
        {
          "text": "as"
        },
        {
          "text": "a"
        },
        {
          "text": "juvenile."
        },
        {
          "text": "The"
        },
        {
          "text": "simplest"
        },
        {
          "text": "explanation"
        },
        {
          "text": "for"
        },
        {
          "text": "this"
        },
        {
          "text": "is"
        },
        {
          "text": "that"
        },
        {
          "text": "the"
        },
        {
          "text": "axolotl"
        },
        {
          "text": "lineage"
        },
        {
          "text": "alone"
        },
        {
          "text": "lost"
        },
        {
          "text": "the"
        },
        {
          "text": "ability"
        },
        {
          "text": "to"
        },
        {
          "text": "metamorphose,"
        },
        {
          "text": "while"
        },
        {
          "text": "others"
        },
        {
          "text": "retained"
        },
        {
          "text": "it."
        },
        {
          "text": "From"
        },
        {
          "text": "a"
        },
        {
          "text": "detailed"
        },
        {
          "text": "analysis"
        },
        {
          "text": "of"
        },
        {
          "text": "the"
        },
        {
          "text": "salamanders’"
        },
        {
          "text": "family"
        },
        {
          "text": "tree,"
        },
        {
          "text": "however,"
        },
        {
          "text": "it"
        },
        {
          "text": "is"
        },
        {
          "text": "clear"
        },
        {
          "text": "that"
        },
        {
          "text": "the"
        },
        {
          "text": "other"
        },
        {
          "text": "lineages"
        },
        {
          "text": "evolved"
        },
        {
          "text": "from"
        },
        {
          "text": "an"
        },
        {
          "text": "ancestor"
        },
        {
          "text": "that"
        },
        {
          "text": "itself"
        },
        {
          "text": "had"
        },
        {
          "text": "lost"
        },
        {
          "text": "the"
        },
        {
          "text": "ability"
        },
        {
          "text": "to"
        },
        {
          "text": "metamorphose."
        },
        {
          "text": "In"
        },
        {
          "text": "other"
        },
        {
          "text": "words,"
        },
        {
          "text": "metamorphosis"
        },
        {
          "text": "in"
        },
        {
          "text": "mole"
        },
        {
          "text": "salamanders"
        },
        {
          "text": "is"
        },
        {
          "text": "an"
        },
        {
          "text": "atavism."
        },
        {
          "text": "The"
        },
        {
          "text": "salamander"
        },
        {
          "text": "example"
        },
        {
          "text": "fits"
        },
        {
          "text": "with"
        },
        {
          "text": "Raff’s"
        },
        {
          "text": "10million-year"
        },
        {
          "text": "time"
        },
        {
          "text": "frame."
        },
        {
          "text": "More"
        },
        {
          "text": "recently,"
        },
        {
          "text": "however,"
        },
        {
          "text": "examples"
        },
        {
          "text": "have"
        },
        {
          "text": "been"
        },
        {
          "text": "reported"
        },
        {
          "text": "that"
        },
        {
          "text": "break"
        },
        {
          "text": "the"
        },
        {
          "text": "time"
        },
        {
          "text": "limit,"
        },
        {
          "text": "suggesting"
        },
        {
          "text": "that"
        },
        {
          "text": "silent"
        },
        {
          "text": "genes"
        },
        {
          "text": "may"
        },
        {
          "text": "not"
        },
        {
          "text": "be"
        },
        {
          "text": "the"
        },
        {
          "text": "whole"
        },
        {
          "text": "story."
        },
        {
          "text": "In"
        },
        {
          "text": "a"
        },
        {
          "text": "paper"
        },
        {
          "text": "published"
        },
        {
          "text": "last"
        },
        {
          "text": "year,"
        },
        {
          "text": "biologist"
        },
        {
          "text": "Gunter"
        },
        {
          "text": "Wagner"
        },
        {
          "text": "of"
        },
        {
          "text": "Yale"
        },
        {
          "text": "University"
        },
        {
          "text": "reported"
        },
        {
          "text": "some"
        },
        {
          "text": "work"
        },
        {
          "text": "on"
        },
        {
          "text": "the"
        },
        {
          "text": "evolutionary"
        },
        {
          "text": "history"
        },
        {
          "text": "of"
        },
        {
          "text": "a"
        },
        {
          "text": "group"
        },
        {
          "text": "of"
        },
        {
          "text": "South"
        },
        {
          "text": "American"
        },
        {
          "text": "lizards"
        },
        {
          "text": "called"
        },
        {
          "text": "Bachia."
        },
        {
          "text": "Many"
        },
        {
          "text": "of"
        },
        {
          "text": "these"
        },
        {
          "text": "have"
        },
        {
          "text": "minuscule"
        },
        {
          "text": "limbs;"
        },
        {
          "text": "some"
        },
        {
          "text": "look"
        },
        {
          "text": "more"
        },
        {
          "text": "like"
        },
        {
          "text": "snakes"
        },
        {
          "text": "than"
        },
        {
          "text": "lizards"
        },
        {
          "text": "and"
        },
        {
          "text": "a"
        },
        {
          "text": "few"
        },
        {
          "text": "have"
        },
        {
          "text": "completely"
        },
        {
          "text": "lost"
        },
        {
          "text": "the"
        },
        {
          "text": "toes"
        },
        {
          "text": "on"
        },
        {
          "text": "their"
        },
        {
          "text": "hind"
        },
        {
          "text": "limbs."
        },
        {
          "text": "Other"
        },
        {
          "text": "species,"
        },
        {
          "text": "however,"
        },
        {
          "text": "sport"
        },
        {
          "text": "up"
        },
        {
          "text": "to"
        },
        {
          "text": "four"
        },
        {
          "text": "toes"
        },
        {
          "text": "on"
        },
        {
          "text": "their"
        },
        {
          "text": "hind"
        },
        {
          "text": "legs."
        },
        {
          "text": "The"
        },
        {
          "text": "simplest"
        },
        {
          "text": "explanation"
        },
        {
          "text": "is"
        },
        {
          "text": "that"
        },
        {
          "text": "the"
        },
        {
          "text": "toed"
        },
        {
          "text": "lineages"
        },
        {
          "text": "never"
        },
        {
          "text": "lost"
        },
        {
          "text": "their"
        },
        {
          "text": "toes,"
        },
        {
          "text": "but"
        },
        {
          "text": "Wagner"
        },
        {
          "text": "begs"
        },
        {
          "text": "to"
        },
        {
          "text": "differ."
        },
        {
          "text": "According"
        },
        {
          "text": "to"
        },
        {
          "text": "his"
        },
        {
          "text": "analysis"
        },
        {
          "text": "of"
        },
        {
          "text": "the"
        },
        {
          "text": "Bachia"
        },
        {
          "text": "family"
        },
        {
          "text": "tree,"
        },
        {
          "text": "the"
        },
        {
          "text": "toed"
        },
        {
          "text": "species"
        },
        {
          "text": "re-evolved"
        },
        {
          "text": "toes"
        },
        {
          "text": "from"
        },
        {
          "text": "toeless"
        },
        {
          "text": "ancestors"
        },
        {
          "text": "and,"
        },
        {
          "text": "what"
        },
        {
          "text": "is"
        },
        {
          "text": "more,"
        },
        {
          "text": "digit"
        },
        {
          "text": "loss"
        },
        {
          "text": "and"
        },
        {
          "text": "gain"
        },
        {
          "text": "has"
        },
        {
          "text": "occurred"
        },
        {
          "text": "on"
        },
        {
          "text": "more"
        },
        {
          "text": "than"
        },
        {
          "text": "one"
        },
        {
          "text": "occasion"
        },
        {
          "text": "over"
        },
        {
          "text": "tens"
        },
        {
          "text": "of"
        },
        {
          "text": "millions"
        },
        {
          "text": "of"
        },
        {
          "text": "years."
        },
        {
          "text": "So"
        },
        {
          "text": "what’s"
        },
        {
          "text": "going"
        },
        {
          "text": "on?"
        },
        {
          "text": "One"
        },
        {
          "text": "possibility"
        },
        {
          "text": "is"
        },
        {
          "text": "that"
        },
        {
          "text": "these"
        },
        {
          "text": "traits"
        },
        {
          "text": "are"
        },
        {
          "text": "lost"
        },
        {
          "text": "and"
        },
        {
          "text": "then"
        },
        {
          "text": "simply"
        },
        {
          "text": "reappear,"
        },
        {
          "text": "in"
        },
        {
          "text": "much"
        },
        {
          "text": "the"
        },
        {
          "text": "same"
        },
        {
          "text": "way"
        },
        {
          "text": "that"
        },
        {
          "text": "similar"
        },
        {
          "text": "structures"
        },
        {
          "text": "can"
        },
        {
          "text": "independently"
        },
        {
          "text": "arise"
        },
        {
          "text": "in"
        },
        {
          "text": "unrelated"
        },
        {
          "text": "species,"
        },
        {
          "text": "such"
        },
        {
          "text": "as"
        },
        {
          "text": "the"
        },
        {
          "text": "dorsal"
        },
        {
          "text": "fins"
        },
        {
          "text": "of"
        },
        {
          "text": "sharks"
        },
        {
          "text": "and"
        },
        {
          "text": "killer"
        },
        {
          "text": "whales."
        },
        {
          "text": "Another"
        },
        {
          "text": "more"
        },
        {
          "text": "intriguing"
        },
        {
          "text": "possibility"
        },
        {
          "text": "is"
        },
        {
          "text": "that"
        },
        {
          "text": "the"
        },
        {
          "text": "genetic"
        },
        {
          "text": "information"
        },
        {
          "text": "needed"
        },
        {
          "text": "to"
        },
        {
          "text": "make"
        },
        {
          "text": "toes"
        },
        {
          "text": "somehow"
        },
        {
          "text": "survived"
        },
        {
          "text": "for"
        },
        {
          "text": "tens"
        },
        {
          "text": "or"
        },
        {
          "text": "perhaps"
        },
        {
          "text": "hundreds"
        },
        {
          "text": "of"
        },
        {
          "text": "millions"
        },
        {
          "text": "of"
        },
        {
          "text": "years"
        },
        {
          "text": "in"
        },
        {
          "text": "the"
        },
        {
          "text": "lizards"
        },
        {
          "text": "and"
        },
        {
          "text": "was"
        },
        {
          "text": "reactivated."
        },
        {
          "text": "These"
        },
        {
          "text": "atavistic"
        },
        {
          "text": "traits"
        },
        {
          "text": "provided"
        },
        {
          "text": "an"
        },
        {
          "text": "advantage"
        },
        {
          "text": "and"
        },
        {
          "text": "spread"
        },
        {
          "text": "through"
        },
        {
          "text": "the"
        },
        {
          "text": "population,"
        },
        {
          "text": "effectively"
        },
        {
          "text": "reversing"
        },
        {
          "text": "evolution."
        },
        {
          "text": "But"
        },
        {
          "text": "if"
        },
        {
          "text": "silent"
        },
        {
          "text": "genes"
        },
        {
          "text": "degrade"
        },
        {
          "text": "within"
        },
        {
          "text": "6"
        },
        {
          "text": "to"
        },
        {
          "text": "million"
        },
        {
          "text": "years,"
        },
        {
          "text": "how"
        },
        {
          "text": "can"
        },
        {
          "text": "long-lost"
        },
        {
          "text": "traits"
        },
        {
          "text": "be"
        },
        {
          "text": "reactivated"
        },
        {
          "text": "over"
        },
        {
          "text": "longer"
        },
        {
          "text": "timescales?"
        },
        {
          "text": "The"
        },
        {
          "text": "answer"
        },
        {
          "text": "may"
        },
        {
          "text": "lie"
        },
        {
          "text": "in"
        },
        {
          "text": "the"
        },
        {
          "text": "womb."
        },
        {
          "text": "Early"
        },
        {
          "text": "embryos"
        },
        {
          "text": "of"
        },
        {
          "text": "many"
        },
        {
          "text": "species"
        },
        {
          "text": "develop"
        },
        {
          "text": "ancestral"
        },
        {
          "text": "features."
        },
        {
          "text": "Snake"
        },
        {
          "text": "embryos,"
        },
        {
          "text": "for"
        },
        {
          "text": "example,"
        },
        {
          "text": "sprout"
        },
        {
          "text": "hind"
        },
        {
          "text": "limb"
        },
        {
          "text": "buds."
        },
        {
          "text": "Later"
        },
        {
          "text": "in"
        },
        {
          "text": "development"
        },
        {
          "text": "these"
        },
        {
          "text": "features"
        },
        {
          "text": "disappear"
        },
        {
          "text": "thanks"
        },
        {
          "text": "to"
        },
        {
          "text": "developmental"
        },
        {
          "text": "programs"
        },
        {
          "text": "that"
        },
        {
          "text": "say"
        },
        {
          "text": "‘lose"
        },
        {
          "text": "the"
        },
        {
          "text": "leg’."
        },
        {
          "text": "If"
        },
        {
          "text": "for"
        },
        {
          "text": "any"
        },
        {
          "text": "reason"
        },
        {
          "text": "this"
        },
        {
          "text": "does"
        },
        {
          "text": "not"
        },
        {
          "text": "happen,"
        },
        {
          "text": "the"
        },
        {
          "text": "ancestral"
        },
        {
          "text": "feature"
        },
        {
          "text": "may"
        },
        {
          "text": "not"
        },
        {
          "text": "disappear,"
        },
        {
          "text": "leading"
        },
        {
          "text": "to"
        },
        {
          "text": "an"
        },
        {
          "text": "atavism."
        }
      ],
      "questionGroups": []
    }
  ]
}